NiukeWangCYuyanRumenZixueZhinanFix1/README.md
NiukeWangCYuyanRumenZixueZhinanFix1/__init__.py
NiukeWangCYuyanRumenZixueZhinanFix1/__main__.py
NiukeWangCYuyanRumenZixueZhinanFix1/file.epub
NiukeWangCYuyanRumenZixueZhinanFix1/index.html
NiukeWangCYuyanRumenZixueZhinanFix1/css/__init__.py
NiukeWangCYuyanRumenZixueZhinanFix1/css/annotations.css
NiukeWangCYuyanRumenZixueZhinanFix1/css/main.css
NiukeWangCYuyanRumenZixueZhinanFix1/css/normalize.css
NiukeWangCYuyanRumenZixueZhinanFix1/css/popup.css
NiukeWangCYuyanRumenZixueZhinanFix1/font/__init__.py
NiukeWangCYuyanRumenZixueZhinanFix1/font/fontello.eot
NiukeWangCYuyanRumenZixueZhinanFix1/font/fontello.svg
NiukeWangCYuyanRumenZixueZhinanFix1/font/fontello.ttf
NiukeWangCYuyanRumenZixueZhinanFix1/font/fontello.woff
NiukeWangCYuyanRumenZixueZhinanFix1/img/__init__.py
NiukeWangCYuyanRumenZixueZhinanFix1/img/annotator-glyph-sprite.png
NiukeWangCYuyanRumenZixueZhinanFix1/img/annotator-icon-sprite.png
NiukeWangCYuyanRumenZixueZhinanFix1/img/apple-touch-icon.png
NiukeWangCYuyanRumenZixueZhinanFix1/img/cancelfullscreen.png
NiukeWangCYuyanRumenZixueZhinanFix1/img/close.png
NiukeWangCYuyanRumenZixueZhinanFix1/img/fullscreen.png
NiukeWangCYuyanRumenZixueZhinanFix1/img/loader.gif
NiukeWangCYuyanRumenZixueZhinanFix1/img/menu-icon.png
NiukeWangCYuyanRumenZixueZhinanFix1/img/save.png
NiukeWangCYuyanRumenZixueZhinanFix1/img/saved.png
NiukeWangCYuyanRumenZixueZhinanFix1/img/settings-s.png
NiukeWangCYuyanRumenZixueZhinanFix1/img/settings.png
NiukeWangCYuyanRumenZixueZhinanFix1/img/star.png
NiukeWangCYuyanRumenZixueZhinanFix1/js/__init__.py
NiukeWangCYuyanRumenZixueZhinanFix1/js/epub.js
NiukeWangCYuyanRumenZixueZhinanFix1/js/epub.min.js
NiukeWangCYuyanRumenZixueZhinanFix1/js/epub.min.map
NiukeWangCYuyanRumenZixueZhinanFix1/js/hooks.min.js
NiukeWangCYuyanRumenZixueZhinanFix1/js/hooks.min.map
NiukeWangCYuyanRumenZixueZhinanFix1/js/reader.js
NiukeWangCYuyanRumenZixueZhinanFix1/js/reader.js.map
NiukeWangCYuyanRumenZixueZhinanFix1/js/reader.min.js
niuke_wang_c_yuyan_rumen_zixue_zhinan_fix1-2025.3.24.0.dist-info/METADATA
niuke_wang_c_yuyan_rumen_zixue_zhinan_fix1-2025.3.24.0.dist-info/WHEEL
niuke_wang_c_yuyan_rumen_zixue_zhinan_fix1-2025.3.24.0.dist-info/entry_points.txt
niuke_wang_c_yuyan_rumen_zixue_zhinan_fix1-2025.3.24.0.dist-info/top_level.txt
niuke_wang_c_yuyan_rumen_zixue_zhinan_fix1-2025.3.24.0.dist-info/RECORD
